leap.bitmask-0.10.1-py2.7-nspkg.pth
leap/bitmask/__init__.py
leap/bitmask/_version.py
leap/bitmask/config.py
leap/bitmask/hooks.py
leap/bitmask/util.py
leap/bitmask/bonafide/__init__.py
leap/bitmask/bonafide/_http.py
leap/bitmask/bonafide/_protocol.py
leap/bitmask/bonafide/_srp.py
leap/bitmask/bonafide/config.py
leap/bitmask/bonafide/cred_srp.py
leap/bitmask/bonafide/errors.py
leap/bitmask/bonafide/provider.py
leap/bitmask/bonafide/service.py
leap/bitmask/bonafide/session.py
leap/bitmask/chrome/__init__.py
leap/bitmask/chrome/chromeapp.py
leap/bitmask/cli/__init__.py
leap/bitmask/cli/bitmask_cli.py
leap/bitmask/cli/command.py
leap/bitmask/cli/keys.py
leap/bitmask/cli/logs.py
leap/bitmask/cli/mail.py
leap/bitmask/cli/provider.py
leap/bitmask/cli/user.py
leap/bitmask/cli/vpn.py
leap/bitmask/cli/webui.py
leap/bitmask/core/__init__.py
leap/bitmask/core/_session.py
leap/bitmask/core/_zmq.py
leap/bitmask/core/api.py
leap/bitmask/core/bitmaskd.tac
leap/bitmask/core/configurable.py
leap/bitmask/core/dispatcher.py
leap/bitmask/core/dummy.py
leap/bitmask/core/flags.py
leap/bitmask/core/launcher.py
leap/bitmask/core/logs.py
leap/bitmask/core/mail_services.py
leap/bitmask/core/manhole.py
leap/bitmask/core/service.py
leap/bitmask/core/uuid_map.py
leap/bitmask/core/websocket.py
leap/bitmask/core/web/__init__.py
leap/bitmask/core/web/_auth.py
leap/bitmask/core/web/api.py
leap/bitmask/core/web/service.py
leap/bitmask/core/web/static/__init__.py
leap/bitmask/gui/__init__.py
leap/bitmask/gui/app.py
leap/bitmask/gui/app2.py
leap/bitmask/gui/app_rc.py
leap/bitmask/keymanager/__init__.py
leap/bitmask/keymanager/documents.py
leap/bitmask/keymanager/errors.py
leap/bitmask/keymanager/keys.py
leap/bitmask/keymanager/migrator.py
leap/bitmask/keymanager/nicknym.py
leap/bitmask/keymanager/openpgp.py
leap/bitmask/keymanager/refresher.py
leap/bitmask/keymanager/validation.py
leap/bitmask/keymanager/wrapper.py
leap.bitmask-0.10.1.dist-info/DESCRIPTION.rst
leap.bitmask-0.10.1.dist-info/METADATA
leap.bitmask-0.10.1.dist-info/RECORD
leap.bitmask-0.10.1.dist-info/WHEEL
leap.bitmask-0.10.1.dist-info/entry_points.txt
leap.bitmask-0.10.1.dist-info/metadata.json
leap.bitmask-0.10.1.dist-info/namespace_packages.txt
leap.bitmask-0.10.1.dist-info/top_level.txt
