Metadata-Version: 2.0
Name: leap.bitmask
Version: 0.10.1
Summary: The Internet Encryption Toolkit: Encrypted Internet Proxy and Encrypted Mail.
Home-page: https://leap.se/
Author: Kali Kaneko
Author-email: kali@leap.se
License: GPLv3+
Download-URL: https://github.com/leapcode/bitmask-dev/archive/0.10.1.tar.gz
Platform: UNKNOWN
Classifier: Development Status :: 4 - Beta
Classifier: Intended Audience :: End Users/Desktop
Classifier: License :: OSI Approved :: GNU General Public License v3 or later (GPLv3+)
Classifier: Operating System :: OS Independent
Classifier: Programming Language :: Python
Classifier: Programming Language :: Python :: 2.7
Classifier: Topic :: Communications
Classifier: Topic :: Communications :: Email
Classifier: Topic :: Security
Classifier: Topic :: Security :: Cryptography
Classifier: Topic :: Utilities
Requires-Dist: certifi
Requires-Dist: colorama
Requires-Dist: cryptography
Requires-Dist: leap.common
Requires-Dist: python-daemon
Requires-Dist: service-identity
Requires-Dist: srp
Requires-Dist: twisted (>=14.0.0)
Requires-Dist: zope.interface
Provides-Extra: all
Requires-Dist: gnupg; extra == 'all'
Requires-Dist: leap.bitmask-js; extra == 'all'
Requires-Dist: leap.pixelated; extra == 'all'
Requires-Dist: leap.pixelated-www; extra == 'all'
Requires-Dist: leap.soledad[client]; extra == 'all'
Requires-Dist: vext.pyqt5; extra == 'all'
Provides-Extra: backend
Requires-Dist: gnupg; extra == 'backend'
Requires-Dist: leap.soledad[client]; extra == 'backend'
Provides-Extra: gui
Requires-Dist: leap.bitmask-js; extra == 'gui'
Requires-Dist: vext.pyqt5; extra == 'gui'
Provides-Extra: mail
Requires-Dist: gnupg; extra == 'mail'
Requires-Dist: leap.soledad[client]; extra == 'mail'
Provides-Extra: pixelated
Requires-Dist: leap.pixelated; extra == 'pixelated'
Requires-Dist: leap.pixelated-www; extra == 'pixelated'
Provides-Extra: tor
Requires-Dist: txtorcon; extra == 'tor'
